bvwx/__init__.py
bvwx/_arithmetic.py
bvwx/_bits.py
bvwx/_bitwise.py
bvwx/_code.py
bvwx/_count.py
bvwx/_enum.py
bvwx/_lbool.py
bvwx/_logical.py
bvwx/_predicate.py
bvwx/_struct.py
bvwx/_unary.py
bvwx/_union.py
bvwx/_util.py
bvwx/_word.py
bvwx-0.20.0.dist-info/METADATA
bvwx-0.20.0.dist-info/WHEEL
bvwx-0.20.0.dist-info/top_level.txt
bvwx-0.20.0.dist-info/RECORD
