Metadata-Version: 2.4
Name: bvwx
Version: 0.20.0
Summary: Bit Vectors With Xes
Project-URL: Repository, https://github.com/cjdrake/bvwx.git
Requires-Python: >=3.12
